LICENSE
MANIFEST.in
README.md
setup.cfg
setup.py
versioneer.py
nbconflux/__init__.py
nbconflux/__main__.py
nbconflux/_version.py
nbconflux/api.py
nbconflux/cli.py
nbconflux/confluence.tpl
nbconflux/exporter.py
nbconflux/filter.py
nbconflux/markdown.py
nbconflux/preprocessor.py
nbconflux.egg-info/PKG-INFO
nbconflux.egg-info/SOURCES.txt
nbconflux.egg-info/dependency_links.txt
nbconflux.egg-info/entry_points.txt
nbconflux.egg-info/requires.txt
nbconflux.egg-info/top_level.txt