Metadata-Version: 2.1
Name: nbconflux
Version: 0.7.0
Summary: Converts Jupyter Notebooks to Atlassian Confluence (R) pages using nbconvert
Home-page: https://github.com/Valassis-Digital-Media/nbconflux
Author: Valassis Digital
License: BSD 3-Clause
Platform: Linux
Platform: Mac OSX
Platform: Windows
